setup.cfg
setup.py
pyrallelize/__init__.py
pyrallelize.egg-info/PKG-INFO
pyrallelize.egg-info/SOURCES.txt
pyrallelize.egg-info/dependency_links.txt
pyrallelize.egg-info/top_level.txt