Metadata-Version: 1.0
Name: pyrallelize
Version: 0.0.2
Summary: Solution to make parallel download with Python
Home-page: http://github.com/EvandroLG/parallelize
Author: EvandroLG
Author-email: evandrolgoncalves@gmail.com
License: MIT
Keywords: parallel,multiprocessing,download,process
Platform: UNKNOWN
